hupipay_sdk/__init__.py
hupipay_sdk/hupi_pay.py
hupi_pay_sdk-0.1.dist-info/LICENSE
hupi_pay_sdk-0.1.dist-info/METADATA
hupi_pay_sdk-0.1.dist-info/WHEEL
hupi_pay_sdk-0.1.dist-info/top_level.txt
hupi_pay_sdk-0.1.dist-info/RECORD
