Metadata-Version: 2.1
Name: hupi_pay_sdk
Version: 0.1
Summary: A brief description of your package
Home-page: https://github.com/your-username/hupi_pay_sdk
Author: yareta
Author-email: yareta2324@gmail.com
Classifier: Programming Language :: Python :: 3
Classifier: License :: OSI Approved :: MIT License
Classifier: Operating System :: OS Independent
Requires-Python: >=3.6
License-File: LICENSE
Requires-Dist: certifi
Requires-Dist: charset-normalizer
Requires-Dist: idna
Requires-Dist: requests
Requires-Dist: urllib3
